pylogik/__init__.py
pylogik/easyocr/__init__.py
pylogik/easyocr/cli.py
pylogik/easyocr/config.py
pylogik/easyocr/craft.py
pylogik/easyocr/craft_utils.py
pylogik/easyocr/detection.py
pylogik/easyocr/detection_db.py
pylogik/easyocr/easyocr.py
pylogik/easyocr/export.py
pylogik/easyocr/imgproc.py
pylogik/easyocr/recognition.py
pylogik/easyocr/utils.py
pylogik/easyocr/DBNet/DBNet.py
pylogik/easyocr/DBNet/README.md
pylogik/easyocr/DBNet/__pycache__/DBNet.cpython-38.pyc
pylogik/easyocr/DBNet/assets/ops/dcn/__init__.py
pylogik/easyocr/DBNet/assets/ops/dcn/setup.py
pylogik/easyocr/DBNet/assets/ops/dcn/__pycache__/__init__.cpython-38.pyc
pylogik/easyocr/DBNet/assets/ops/dcn/__pycache__/setup.cpython-38.pyc
pylogik/easyocr/DBNet/assets/ops/dcn/functions/__init__.py
pylogik/easyocr/DBNet/assets/ops/dcn/functions/deform_conv.py
pylogik/easyocr/DBNet/assets/ops/dcn/functions/deform_pool.py
pylogik/easyocr/DBNet/assets/ops/dcn/functions/__pycache__/__init__.cpython-38.pyc
pylogik/easyocr/DBNet/assets/ops/dcn/functions/__pycache__/deform_conv.cpython-38.pyc
pylogik/easyocr/DBNet/assets/ops/dcn/functions/__pycache__/deform_pool.cpython-38.pyc
pylogik/easyocr/DBNet/assets/ops/dcn/modules/__init__.py
pylogik/easyocr/DBNet/assets/ops/dcn/modules/deform_conv.py
pylogik/easyocr/DBNet/assets/ops/dcn/modules/deform_pool.py
pylogik/easyocr/DBNet/assets/ops/dcn/modules/__pycache__/__init__.cpython-38.pyc
pylogik/easyocr/DBNet/assets/ops/dcn/modules/__pycache__/deform_conv.cpython-38.pyc
pylogik/easyocr/DBNet/assets/ops/dcn/modules/__pycache__/deform_pool.cpython-38.pyc
pylogik/easyocr/DBNet/assets/ops/dcn/src/deform_conv_cpu.cpp
pylogik/easyocr/DBNet/assets/ops/dcn/src/deform_conv_cpu_kernel.cpp
pylogik/easyocr/DBNet/assets/ops/dcn/src/deform_conv_cpu_kernel.h
pylogik/easyocr/DBNet/assets/ops/dcn/src/deform_conv_cuda.cpp
pylogik/easyocr/DBNet/assets/ops/dcn/src/deform_conv_cuda_kernel.cu
pylogik/easyocr/DBNet/assets/ops/dcn/src/deform_pool_cpu.cpp
pylogik-0.0.17.dist-info/LICENSE.txt
pylogik-0.0.17.dist-info/METADATA
pylogik-0.0.17.dist-info/WHEEL
pylogik-0.0.17.dist-info/top_level.txt
pylogik-0.0.17.dist-info/RECORD
