Metadata-Version: 2.1
Name: pylogik
Version: 0.0.17
Summary: A collection of image and statistical processing functions and classes
Author: Adrienne Kline
Author-email: askline1@gmail.com
License: MIT
Classifier: Programming Language :: Python :: 3.9
Classifier: License :: OSI Approved :: MIT License
Classifier: Operating System :: OS Independent
License-File: LICENSE.txt
Requires-Dist: matplotlib
Requires-Dist: numpy
Requires-Dist: opencv-python
Requires-Dist: pandas
Requires-Dist: pydicom
Requires-Dist: scipy
Requires-Dist: sympy
Requires-Dist: torch
Requires-Dist: torchvision
Requires-Dist: onnx
Requires-Dist: onnxruntime
Requires-Dist: pathlib2
Requires-Dist: packaging
Requires-Dist: pyclipper
Requires-Dist: opencv-python-headless
Requires-Dist: Pillow
Requires-Dist: python-bidi
Requires-Dist: PyYAML
Requires-Dist: scikit-image
Requires-Dist: Shapely
Requires-Dist: setuptools
Requires-Dist: six
